{"updated":"2026/06/30","records":[{"stock_code":"1301","stock_name":"台塑","ex_dividend_date":"06 / 30","ex_type":"息","cash_dividend_value":0.5,"current_yield_value":0.96,"closing_price_value":52.2,"pe_value":null,"pb_value":0.85},{"stock_code":"1410","stock_name":"南染","ex_dividend_date":"06 / 30","ex_type":"息","cash_dividend_value":0.2,"current_yield_value":0.8,"closing_price_value":24.85,"pe_value":46.02,"pb_value":1.47},{"stock_code":"1521","stock_name":"大億","ex_dividend_date":"06 / 30","ex_type":"息","cash_dividend_value":0.75,"current_yield_value":2.9,"closing_price_value":25.9,"pe_value":36.48,"pb_value":1.07},{"stock_code":"1598","stock_name":"岱宇","ex_dividend_date":"06 / 30","ex_type":"息","cash_dividend_value":0.5,"current_yield_value":2.6,"closing_price_value":19.2,"pe_value":null,"pb_value":0.76},{"stock_code":"1727","stock_name":"中華化","ex_dividend_date":"06 / 30","ex_type":"息","cash_dividend_value":0.15,"current_yield_value":0.17,"closing_price_value":88.0,"pe_value":237.84,"pb_value":5.34},{"stock_code":"1731","stock_name":"美吾華","ex_dividend_date":"06 / 30","ex_type":"息","cash_dividend_value":1.22,"current_yield_value":5.6,"closing_price_value":21.8,"pe_value":15.57,"pb_value":1.3},{"stock_code":"1817","stock_name":"凱撒衛","ex_dividend_date":"06 / 30","ex_type":"息","cash_dividend_value":2.2,"current_yield_value":5.53,"closing_price_value":39.8,"pe_value":9.5,"pb_value":1.22},{"stock_code":"2328","stock_name":"廣宇","ex_dividend_date":"06 / 30","ex_type":"息","cash_dividend_value":0.9,"current_yield_value":1.88,"closing_price_value":48.0,"pe_value":48.98,"pb_value":1.66},{"stock_code":"2397","stock_name":"友通","ex_dividend_date":"06 / 30","ex_type":"息","cash_dividend_value":2.45,"current_yield_value":4.28,"closing_price_value":57.2,"pe_value":24.66,"pb_value":2.03},{"stock_code":"2436","stock_name":"偉詮電","ex_dividend_date":"06 / 30","ex_type":"息","cash_dividend_value":1.956716,"current_yield_value":2.76,"closing_price_value":70.8,"pe_value":21.01,"pb_value":3.22},{"stock_code":"2605","stock_name":"新興","ex_dividend_date":"06 / 30","ex_type":"息","cash_dividend_value":1.0,"current_yield_value":3.41,"closing_price_value":29.3,"pe_value":14.02,"pb_value":0.97},{"stock_code":"2882","stock_name":"國泰金","ex_dividend_date":"06 / 30","ex_type":"息","cash_dividend_value":3.5,"current_yield_value":3.3,"closing_price_value":106.0,"pe_value":16.08,"pb_value":2.12},{"stock_code":"2882A","stock_name":"國泰特","ex_dividend_date":"06 / 30","ex_type":"息","cash_dividend_value":2.526,"current_yield_value":null,"closing_price_value":null,"pe_value":null,"pb_value":null},{"stock_code":"2882B","stock_name":"國泰金乙特","ex_dividend_date":"06 / 30","ex_type":"息","cash_dividend_value":2.280657,"current_yield_value":null,"closing_price_value":null,"pe_value":null,"pb_value":null},{"stock_code":"2883","stock_name":"凱基金","ex_dividend_date":"06 / 30","ex_type":"息","cash_dividend_value":1.0,"current_yield_value":3.34,"closing_price_value":29.9,"pe_value":16.8,"pb_value":1.5},{"stock_code":"2883B","stock_name":"凱基金乙特","ex_dividend_date":"06 / 30","ex_type":"息","cash_dividend_value":0.355,"current_yield_value":null,"closing_price_value":null,"pe_value":null,"pb_value":null},{"stock_code":"3416","stock_name":"融程電","ex_dividend_date":"06 / 30","ex_type":"息","cash_dividend_value":5.095945,"current_yield_value":3.12,"closing_price_value":163.5,"pe_value":22.4,"pb_value":4.05},{"stock_code":"3714","stock_name":"富采","ex_dividend_date":"06 / 30","ex_type":"息","cash_dividend_value":0.9,"current_yield_value":1.46,"closing_price_value":61.6,"pe_value":null,"pb_value":1.09},{"stock_code":"4722","stock_name":"國精化","ex_dividend_date":"06 / 30","ex_type":"息","cash_dividend_value":1.184076,"current_yield_value":0.41,"closing_price_value":289.5,"pe_value":171.3,"pb_value":9.48},{"stock_code":"6592","stock_name":"和潤企業","ex_dividend_date":"06 / 30","ex_type":"權息","cash_dividend_value":3.0,"current_yield_value":4.65,"closing_price_value":64.5,"pe_value":13.11,"pb_value":1.25},{"stock_code":"6592A","stock_name":"和潤企業甲特","ex_dividend_date":"06 / 30","ex_type":"息","cash_dividend_value":4.2,"current_yield_value":null,"closing_price_value":null,"pe_value":null,"pb_value":null},{"stock_code":"6592B","stock_name":"和潤企業乙特","ex_dividend_date":"06 / 30","ex_type":"息","cash_dividend_value":4.5,"current_yield_value":null,"closing_price_value":null,"pe_value":null,"pb_value":null},{"stock_code":"6835","stock_name":"圓裕","ex_dividend_date":"06 / 30","ex_type":"息","cash_dividend_value":1.006755,"current_yield_value":2.84,"closing_price_value":35.45,"pe_value":272.69,"pb_value":1.31},{"stock_code":"7711","stock_name":"永擎","ex_dividend_date":"06 / 30","ex_type":"息","cash_dividend_value":8.987093,"current_yield_value":2.8,"closing_price_value":320.5,"pe_value":28.62,"pb_value":4.84},{"stock_code":"8039","stock_name":"台虹","ex_dividend_date":"06 / 30","ex_type":"息","cash_dividend_value":1.993351,"current_yield_value":1.45,"closing_price_value":137.5,"pe_value":58.02,"pb_value":3.42},{"stock_code":"9931","stock_name":"欣高","ex_dividend_date":"06 / 30","ex_type":"息","cash_dividend_value":1.8,"current_yield_value":5.17,"closing_price_value":34.8,"pe_value":14.62,"pb_value":1.21},{"stock_code":"1101","stock_name":"台泥","ex_dividend_date":"07 / 01","ex_type":"息","cash_dividend_value":0.8,"current_yield_value":3.31,"closing_price_value":24.15,"pe_value":null,"pb_value":0.77},{"stock_code":"1101B","stock_name":"台泥乙特","ex_dividend_date":"07 / 01","ex_type":"息","cash_dividend_value":2.02625,"current_yield_value":null,"closing_price_value":null,"pe_value":null,"pb_value":null},{"stock_code":"1470","stock_name":"大統新創","ex_dividend_date":"07 / 01","ex_type":"息","cash_dividend_value":0.65,"current_yield_value":2.97,"closing_price_value":21.85,"pe_value":25.11,"pb_value":1.9},{"stock_code":"1725","stock_name":"元禎","ex_dividend_date":"07 / 01","ex_type":"息","cash_dividend_value":1.07,"current_yield_value":3.09,"closing_price_value":34.6,"pe_value":21.36,"pb_value":0.94},{"stock_code":"2302","stock_name":"麗正","ex_dividend_date":"07 / 01","ex_type":"息","cash_dividend_value":0.35,"current_yield_value":0.74,"closing_price_value":47.1,"pe_value":59.62,"pb_value":4.39},{"stock_code":"2357","stock_name":"華碩","ex_dividend_date":"07 / 01","ex_type":"息","cash_dividend_value":42.0,"current_yield_value":5.99,"closing_price_value":701.0,"pe_value":12.53,"pb_value":1.81},{"stock_code":"2881","stock_name":"富邦金","ex_dividend_date":"07 / 01","ex_type":"息","cash_dividend_value":4.25,"current_yield_value":3.17,"closing_price_value":134.0,"pe_value":18.43,"pb_value":2.05},{"stock_code":"2881A","stock_name":"富邦特","ex_dividend_date":"07 / 01","ex_type":"息","cash_dividend_value":2.74875,"current_yield_value":null,"closing_price_value":null,"pe_value":null,"pb_value":null},{"stock_code":"2881B","stock_name":"富邦金乙特","ex_dividend_date":"07 / 01","ex_type":"息","cash_dividend_value":2.572356,"current_yield_value":null,"closing_price_value":null,"pe_value":null,"pb_value":null},{"stock_code":"2881C","stock_name":"富邦金丙特","ex_dividend_date":"07 / 01","ex_type":"息","cash_dividend_value":1.8,"current_yield_value":null,"closing_price_value":null,"pe_value":null,"pb_value":null},{"stock_code":"2884","stock_name":"玉山金","ex_dividend_date":"07 / 01","ex_type":"息","cash_dividend_value":1.4,"current_yield_value":4.05,"closing_price_value":34.55,"pe_value":15.7,"pb_value":1.96},{"stock_code":"2887E","stock_name":"台新新光戊特一","ex_dividend_date":"07 / 01","ex_type":"息","cash_dividend_value":2.43625,"current_yield_value":null,"closing_price_value":null,"pe_value":null,"pb_value":null},{"stock_code":"2887F","stock_name":"台新新光戊特二","ex_dividend_date":"07 / 01","ex_type":"息","cash_dividend_value":1.933601,"current_yield_value":null,"closing_price_value":null,"pe_value":null,"pb_value":null},{"stock_code":"2887G","stock_name":"台新新光庚特一","ex_dividend_date":"07 / 01","ex_type":"息","cash_dividend_value":1.71,"current_yield_value":null,"closing_price_value":null,"pe_value":null,"pb_value":null},{"stock_code":"2887H","stock_name":"台新新光庚特二","ex_dividend_date":"07 / 01","ex_type":"息","cash_dividend_value":1.8,"current_yield_value":null,"closing_price_value":null,"pe_value":null,"pb_value":null},{"stock_code":"2887I","stock_name":"台新新光辛特","ex_dividend_date":"07 / 01","ex_type":"息","cash_dividend_value":0.073442,"current_yield_value":null,"closing_price_value":null,"pe_value":null,"pb_value":null},{"stock_code":"2903","stock_name":"遠百","ex_dividend_date":"07 / 01","ex_type":"息","cash_dividend_value":1.25,"current_yield_value":5.4,"closing_price_value":23.15,"pe_value":14.29,"pb_value":1.04},{"stock_code":"3515","stock_name":"華擎","ex_dividend_date":"07 / 01","ex_type":"息","cash_dividend_value":11.001795,"current_yield_value":4.74,"closing_price_value":232.0,"pe_value":14.64,"pb_value":2.54},{"stock_code":"3607","stock_name":"谷崧","ex_dividend_date":"07 / 01","ex_type":"息","cash_dividend_value":0.8,"current_yield_value":4.97,"closing_price_value":16.1,"pe_value":41.28,"pb_value":1.16},{"stock_code":"4119","stock_name":"旭富","ex_dividend_date":"07 / 01","ex_type":"息","cash_dividend_value":0.75,"current_yield_value":1.69,"closing_price_value":44.5,"pe_value":55.63,"pb_value":0.98},{"stock_code":"4755","stock_name":"三福化","ex_dividend_date":"07 / 01","ex_type":"息","cash_dividend_value":3.7,"current_yield_value":2.78,"closing_price_value":133.0,"pe_value":36.84,"pb_value":2.4},{"stock_code":"4961","stock_name":"天鈺","ex_dividend_date":"07 / 01","ex_type":"息","cash_dividend_value":7.72,"current_yield_value":4.68,"closing_price_value":165.0,"pe_value":19.78,"pb_value":1.12},{"stock_code":"6285","stock_name":"啟碁","ex_dividend_date":"07 / 01","ex_type":"息","cash_dividend_value":4.301769,"current_yield_value":1.82,"closing_price_value":236.0,"pe_value":34.81,"pb_value":3.26},{"stock_code":"6655","stock_name":"科定","ex_dividend_date":"07 / 01","ex_type":"息","cash_dividend_value":4.8,"current_yield_value":3.97,"closing_price_value":121.0,"pe_value":29.8,"pb_value":3.53},{"stock_code":"8271","stock_name":"宇瞻","ex_dividend_date":"07 / 01","ex_type":"息","cash_dividend_value":4.448443,"current_yield_value":2.25,"closing_price_value":198.0,"pe_value":9.65,"pb_value":4.02},{"stock_code":"8482","stock_name":"商億-KY","ex_dividend_date":"07 / 01","ex_type":"息","cash_dividend_value":1.96,"current_yield_value":null,"closing_price_value":null,"pe_value":null,"pb_value":null},{"stock_code":"00939","stock_name":"統一台灣高息動能","ex_dividend_date":"07 / 02","ex_type":"息","cash_dividend_value":null,"current_yield_value":null,"closing_price_value":null,"pe_value":null,"pb_value":null},{"stock_code":"00984D","stock_name":"主動聯博全球非投","ex_dividend_date":"07 / 02","ex_type":"息","cash_dividend_value":null,"current_yield_value":null,"closing_price_value":null,"pe_value":null,"pb_value":null},{"stock_code":"1452","stock_name":"宏益","ex_dividend_date":"07 / 02","ex_type":"息","cash_dividend_value":0.2,"current_yield_value":1.85,"closing_price_value":10.8,"pe_value":null,"pb_value":0.54},{"stock_code":"1612","stock_name":"宏泰","ex_dividend_date":"07 / 02","ex_type":"息","cash_dividend_value":2.5,"current_yield_value":6.75,"closing_price_value":37.05,"pe_value":12.35,"pb_value":1.44},{"stock_code":"1752","stock_name":"南光","ex_dividend_date":"07 / 02","ex_type":"息","cash_dividend_value":1.6,"current_yield_value":4.91,"closing_price_value":32.6,"pe_value":16.06,"pb_value":1.4},{"stock_code":"1789","stock_name":"神隆","ex_dividend_date":"07 / 02","ex_type":"息","cash_dividend_value":0.29,"current_yield_value":1.45,"closing_price_value":20.0,"pe_value":142.86,"pb_value":1.53},{"stock_code":"2010","stock_name":"春源","ex_dividend_date":"07 / 02","ex_type":"息","cash_dividend_value":2.0,"current_yield_value":8.35,"closing_price_value":23.95,"pe_value":10.28,"pb_value":1.28},{"stock_code":"2317","stock_name":"鴻海","ex_dividend_date":"07 / 02","ex_type":"息","cash_dividend_value":7.171792,"current_yield_value":2.89,"closing_price_value":248.5,"pe_value":17.65,"pb_value":1.95},{"stock_code":"2354","stock_name":"鴻準","ex_dividend_date":"07 / 02","ex_type":"息","cash_dividend_value":1.5,"current_yield_value":2.73,"closing_price_value":54.9,"pe_value":26.02,"pb_value":0.73},{"stock_code":"2433","stock_name":"互盛電","ex_dividend_date":"07 / 02","ex_type":"息","cash_dividend_value":2.7,"current_yield_value":6.1,"closing_price_value":44.25,"pe_value":14.51,"pb_value":2.08},{"stock_code":"2462","stock_name":"良得電","ex_dividend_date":"07 / 02","ex_type":"息","cash_dividend_value":0.2,"current_yield_value":0.84,"closing_price_value":23.8,"pe_value":340.0,"pb_value":1.07},{"stock_code":"2607","stock_name":"榮運","ex_dividend_date":"07 / 02","ex_type":"息","cash_dividend_value":2.7,"current_yield_value":5.57,"closing_price_value":48.45,"pe_value":10.24,"pb_value":0.82},{"stock_code":"2753","stock_name":"八方雲集","ex_dividend_date":"07 / 02","ex_type":"息","cash_dividend_value":7.5,"current_yield_value":3.95,"closing_price_value":190.0,"pe_value":14.11,"pb_value":3.57},{"stock_code":"2820","stock_name":"華票","ex_dividend_date":"07 / 02","ex_type":"息","cash_dividend_value":0.9,"current_yield_value":5.06,"closing_price_value":17.8,"pe_value":11.71,"pb_value":0.86},{"stock_code":"3006","stock_name":"晶豪科","ex_dividend_date":"07 / 02","ex_type":"息","cash_dividend_value":1.0,"current_yield_value":0.44,"closing_price_value":227.0,"pe_value":26.99,"pb_value":4.95},{"stock_code":"3090","stock_name":"日電貿","ex_dividend_date":"07 / 02","ex_type":"息","cash_dividend_value":4.8,"current_yield_value":1.55,"closing_price_value":310.0,"pe_value":64.58,"pb_value":5.06},{"stock_code":"3189","stock_name":"景碩","ex_dividend_date":"07 / 02","ex_type":"息","cash_dividend_value":1.517564,"current_yield_value":0.19,"closing_price_value":797.0,"pe_value":224.51,"pb_value":9.73},{"stock_code":"3311","stock_name":"閎暉","ex_dividend_date":"07 / 02","ex_type":"息","cash_dividend_value":0.6,"current_yield_value":1.62,"closing_price_value":36.95,"pe_value":23.84,"pb_value":0.99},{"stock_code":"3592","stock_name":"瑞鼎","ex_dividend_date":"07 / 02","ex_type":"息","cash_dividend_value":14.6,"current_yield_value":5.54,"closing_price_value":263.5,"pe_value":16.47,"pb_value":1.86},{"stock_code":"3703","stock_name":"欣陸","ex_dividend_date":"07 / 02","ex_type":"息","cash_dividend_value":1.05,"current_yield_value":4.92,"closing_price_value":21.35,"pe_value":10.26,"pb_value":0.64},{"stock_code":"3715","stock_name":"定穎投控","ex_dividend_date":"07 / 02","ex_type":"息","cash_dividend_value":1.08,"current_yield_value":0.64,"closing_price_value":168.5,"pe_value":173.71,"pb_value":4.44},{"stock_code":"4137","stock_name":"麗豐-KY","ex_dividend_date":"07 / 02","ex_type":"息","cash_dividend_value":10.0,"current_yield_value":9.26,"closing_price_value":108.0,"pe_value":13.74,"pb_value":1.6},{"stock_code":"6136","stock_name":"富爾特","ex_dividend_date":"07 / 02","ex_type":"息","cash_dividend_value":1.16,"current_yield_value":4.62,"closing_price_value":25.1,"pe_value":29.88,"pb_value":0.74},{"stock_code":"6197","stock_name":"佳必琪","ex_dividend_date":"07 / 02","ex_type":"息","cash_dividend_value":6.923259,"current_yield_value":1.9,"closing_price_value":364.0,"pe_value":35.51,"pb_value":9.74},{"stock_code":"6213","stock_name":"聯茂","ex_dividend_date":"07 / 02","ex_type":"息","cash_dividend_value":2.998927,"current_yield_value":0.87,"closing_price_value":346.5,"pe_value":84.72,"pb_value":5.97},{"stock_code":"6715","stock_name":"嘉基","ex_dividend_date":"07 / 02","ex_type":"息","cash_dividend_value":1.943104,"current_yield_value":0.43,"closing_price_value":455.0,"pe_value":215.64,"pb_value":8.35},{"stock_code":"8081","stock_name":"致新","ex_dividend_date":"07 / 02","ex_type":"息","cash_dividend_value":16.0,"current_yield_value":5.29,"closing_price_value":302.5,"pe_value":17.22,"pb_value":3.58},{"stock_code":"8926","stock_name":"台汽電","ex_dividend_date":"07 / 02","ex_type":"息","cash_dividend_value":2.119737,"current_yield_value":2.78,"closing_price_value":76.2,"pe_value":18.68,"pb_value":3.19},{"stock_code":"9904","stock_name":"寶成","ex_dividend_date":"07 / 02","ex_type":"息","cash_dividend_value":1.3,"current_yield_value":5.14,"closing_price_value":25.3,"pe_value":6.97,"pb_value":0.49},{"stock_code":"9939","stock_name":"宏全","ex_dividend_date":"07 / 02","ex_type":"息","cash_dividend_value":6.2,"current_yield_value":4.81,"closing_price_value":129.0,"pe_value":14.3,"pb_value":2.01},{"stock_code":"1455","stock_name":"集盛","ex_dividend_date":"07 / 03","ex_type":"息","cash_dividend_value":0.16,"current_yield_value":1.68,"closing_price_value":9.53,"pe_value":null,"pb_value":0.88},{"stock_code":"1730","stock_name":"花仙子","ex_dividend_date":"07 / 03","ex_type":"息","cash_dividend_value":3.0,"current_yield_value":5.6,"closing_price_value":53.6,"pe_value":11.58,"pb_value":1.57},{"stock_code":"2013","stock_name":"中鋼構","ex_dividend_date":"07 / 03","ex_type":"息","cash_dividend_value":2.4,"current_yield_value":5.49,"closing_price_value":43.75,"pe_value":13.54,"pb_value":1.5},{"stock_code":"2425","stock_name":"承啟","ex_dividend_date":"07 / 03","ex_type":"息","cash_dividend_value":0.1,"current_yield_value":0.25,"closing_price_value":39.45,"pe_value":null,"pb_value":1.52},{"stock_code":"2838A","stock_name":"聯邦銀甲特","ex_dividend_date":"07 / 03","ex_type":"息","cash_dividend_value":2.630625,"current_yield_value":null,"closing_price_value":null,"pe_value":null,"pb_value":null},{"stock_code":"2945","stock_name":"三商家購","ex_dividend_date":"07 / 03","ex_type":"息","cash_dividend_value":1.5,"current_yield_value":3.49,"closing_price_value":43.0,"pe_value":19.11,"pb_value":1.51},{"stock_code":"3711","stock_name":"日月光投控","ex_dividend_date":"07 / 03","ex_type":"息","cash_dividend_value":6.584838,"current_yield_value":1.04,"closing_price_value":632.0,"pe_value":58.68,"pb_value":7.91},{"stock_code":"910861","stock_name":"神州-DR","ex_dividend_date":"07 / 03","ex_type":"息","cash_dividend_value":0.072018,"current_yield_value":null,"closing_price_value":null,"pe_value":null,"pb_value":null},{"stock_code":"00946","stock_name":"群益科技高息成長","ex_dividend_date":"07 / 06","ex_type":"息","cash_dividend_value":null,"current_yield_value":null,"closing_price_value":null,"pe_value":null,"pb_value":null},{"stock_code":"00953B","stock_name":"群益優選非投等債","ex_dividend_date":"07 / 06","ex_type":"息","cash_dividend_value":null,"current_yield_value":null,"closing_price_value":null,"pe_value":null,"pb_value":null},{"stock_code":"00985B","stock_name":"群益ESG投等債0-5","ex_dividend_date":"07 / 06","ex_type":"息","cash_dividend_value":null,"current_yield_value":null,"closing_price_value":null,"pe_value":null,"pb_value":null},{"stock_code":"00997A","stock_name":"主動群益美國增長","ex_dividend_date":"07 / 06","ex_type":"息","cash_dividend_value":null,"current_yield_value":null,"closing_price_value":null,"pe_value":null,"pb_value":null},{"stock_code":"1307","stock_name":"三芳","ex_dividend_date":"07 / 06","ex_type":"息","cash_dividend_value":2.2,"current_yield_value":6.4,"closing_price_value":34.35,"pe_value":12.54,"pb_value":1.4},{"stock_code":"2373","stock_name":"震旦行","ex_dividend_date":"07 / 06","ex_type":"息","cash_dividend_value":3.7,"current_yield_value":6.37,"closing_price_value":58.1,"pe_value":14.9,"pb_value":1.85},{"stock_code":"2474","stock_name":"可成","ex_dividend_date":"07 / 06","ex_type":"息","cash_dividend_value":7.113868,"current_yield_value":3.56,"closing_price_value":200.0,"pe_value":19.16,"pb_value":0.79},{"stock_code":"2615","stock_name":"萬海","ex_dividend_date":"07 / 06","ex_type":"息","cash_dividend_value":3.0,"current_yield_value":3.91,"closing_price_value":76.7,"pe_value":7.08,"pb_value":0.75},{"stock_code":"2904","stock_name":"匯僑","ex_dividend_date":"07 / 06","ex_type":"息","cash_dividend_value":0.7,"current_yield_value":4.95,"closing_price_value":14.15,"pe_value":24.4,"pb_value":0.89},{"stock_code":"3037","stock_name":"欣興","ex_dividend_date":"07 / 06","ex_type":"息","cash_dividend_value":1.980153,"current_yield_value":0.2,"closing_price_value":975.0,"pe_value":143.38,"pb_value":13.66},{"stock_code":"3557","stock_name":"嘉威","ex_dividend_date":"07 / 06","ex_type":"息","cash_dividend_value":0.3,"current_yield_value":1.19,"closing_price_value":25.3,"pe_value":null,"pb_value":0.84},{"stock_code":"3704","stock_name":"合勤控","ex_dividend_date":"07 / 06","ex_type":"息","cash_dividend_value":0.4,"current_yield_value":0.93,"closing_price_value":43.0,"pe_value":37.39,"pb_value":1.49},{"stock_code":"5538","stock_name":"東明-KY","ex_dividend_date":"07 / 06","ex_type":"息","cash_dividend_value":1.5,"current_yield_value":4.61,"closing_price_value":32.55,"pe_value":9.43,"pb_value":0.83},{"stock_code":"6155","stock_name":"鈞寶","ex_dividend_date":"07 / 06","ex_type":"息","cash_dividend_value":0.8,"current_yield_value":0.93,"closing_price_value":86.1,"pe_value":172.2,"pb_value":4.72},{"stock_code":"6754","stock_name":"匯僑設計","ex_dividend_date":"07 / 06","ex_type":"息","cash_dividend_value":3.5,"current_yield_value":7.95,"closing_price_value":44.0,"pe_value":13.58,"pb_value":1.36},{"stock_code":"7705","stock_name":"三商餐飲","ex_dividend_date":"07 / 06","ex_type":"息","cash_dividend_value":1.6,"current_yield_value":5.07,"closing_price_value":31.55,"pe_value":14.15,"pb_value":1.33},{"stock_code":"8072","stock_name":"陞泰","ex_dividend_date":"07 / 06","ex_type":"息","cash_dividend_value":1.0,"current_yield_value":3.45,"closing_price_value":29.0,"pe_value":28.43,"pb_value":1.03},{"stock_code":"8112","stock_name":"至上","ex_dividend_date":"07 / 06","ex_type":"權息","cash_dividend_value":3.800548,"current_yield_value":4.17,"closing_price_value":91.2,"pe_value":10.99,"pb_value":2.6},{"stock_code":"8112A","stock_name":"至上甲特","ex_dividend_date":"07 / 06","ex_type":"權息","cash_dividend_value":2.025,"current_yield_value":null,"closing_price_value":null,"pe_value":null,"pb_value":null},{"stock_code":"8476","stock_name":"台境*","ex_dividend_date":"07 / 06","ex_type":"息","cash_dividend_value":0.2,"current_yield_value":0.84,"closing_price_value":23.8,"pe_value":56.67,"pb_value":2.07},{"stock_code":"9935","stock_name":"慶豐富","ex_dividend_date":"07 / 06","ex_type":"息","cash_dividend_value":1.2,"current_yield_value":6.35,"closing_price_value":18.9,"pe_value":11.52,"pb_value":1.28},{"stock_code":"9943","stock_name":"好樂迪","ex_dividend_date":"07 / 06","ex_type":"息","cash_dividend_value":3.5,"current_yield_value":6.18,"closing_price_value":56.6,"pe_value":15.72,"pb_value":1.94},{"stock_code":"2408","stock_name":"南亞科","ex_dividend_date":"07 / 07","ex_type":"息","cash_dividend_value":1.347149,"current_yield_value":0.3,"closing_price_value":449.0,"pe_value":40.2,"pb_value":7.21},{"stock_code":"2417","stock_name":"圓剛","ex_dividend_date":"07 / 07","ex_type":"息","cash_dividend_value":0.250119,"current_yield_value":0.59,"closing_price_value":42.65,"pe_value":164.04,"pb_value":1.97},{"stock_code":"2454","stock_name":"聯發科","ex_dividend_date":"07 / 07","ex_type":"息","cash_dividend_value":24.500215,"current_yield_value":0.63,"closing_price_value":3880.0,"pe_value":61.83,"pb_value":15.87},{"stock_code":"2536","stock_name":"宏普","ex_dividend_date":"07 / 07","ex_type":"息","cash_dividend_value":2.0,"current_yield_value":9.52,"closing_price_value":21.0,"pe_value":6.34,"pb_value":0.55},{"stock_code":"3048","stock_name":"益登","ex_dividend_date":"07 / 07","ex_type":"息","cash_dividend_value":1.0,"current_yield_value":1.59,"closing_price_value":63.0,"pe_value":22.66,"pb_value":2.91},{"stock_code":"6257","stock_name":"矽格","ex_dividend_date":"07 / 07","ex_type":"息","cash_dividend_value":4.249688,"current_yield_value":1.9,"closing_price_value":224.0,"pe_value":33.48,"pb_value":4.96},{"stock_code":"6526","stock_name":"達發","ex_dividend_date":"07 / 07","ex_type":"息","cash_dividend_value":13.5,"current_yield_value":2.16,"closing_price_value":626.0,"pe_value":35.94,"pb_value":5.85},{"stock_code":"6591","stock_name":"動力-KY","ex_dividend_date":"07 / 07","ex_type":"息","cash_dividend_value":4.0,"current_yield_value":7.55,"closing_price_value":53.0,"pe_value":12.35,"pb_value":1.01},{"stock_code":"6862","stock_name":"三集瑞-KY","ex_dividend_date":"07 / 07","ex_type":"息","cash_dividend_value":5.0,"current_yield_value":2.66,"closing_price_value":188.0,"pe_value":30.82,"pb_value":3.01},{"stock_code":"9945","stock_name":"潤泰新","ex_dividend_date":"07 / 07","ex_type":"息","cash_dividend_value":1.1,"current_yield_value":4.14,"closing_price_value":26.6,"pe_value":7.47,"pb_value":0.66},{"stock_code":"1229","stock_name":"聯華","ex_dividend_date":"07 / 08","ex_type":"權息","cash_dividend_value":1.801172,"current_yield_value":4.24,"closing_price_value":42.45,"pe_value":16.33,"pb_value":1.37},{"stock_code":"1303","stock_name":"南亞","ex_dividend_date":"07 / 08","ex_type":"息","cash_dividend_value":0.8,"current_yield_value":0.54,"closing_price_value":148.0,"pe_value":64.07,"pb_value":3.06},{"stock_code":"2028","stock_name":"威致","ex_dividend_date":"07 / 08","ex_type":"息","cash_dividend_value":0.2,"current_yield_value":1.25,"closing_price_value":16.0,"pe_value":45.71,"pb_value":1.09},{"stock_code":"2049","stock_name":"上銀","ex_dividend_date":"07 / 08","ex_type":"息","cash_dividend_value":2.0,"current_yield_value":0.65,"closing_price_value":307.0,"pe_value":66.88,"pb_value":2.89},{"stock_code":"2303","stock_name":"聯電","ex_dividend_date":"07 / 08","ex_type":"息","cash_dividend_value":2.608082,"current_yield_value":1.59,"closing_price_value":164.0,"pe_value":41.21,"pb_value":5.07},{"stock_code":"2405","stock_name":"輔信","ex_dividend_date":"07 / 08","ex_type":"息","cash_dividend_value":0.1,"current_yield_value":0.59,"closing_price_value":17.05,"pe_value":null,"pb_value":1.69},{"stock_code":"2545","stock_name":"皇翔","ex_dividend_date":"07 / 08","ex_type":"息","cash_dividend_value":2.8,"current_yield_value":7.43,"closing_price_value":37.7,"pe_value":25.47,"pb_value":0.96},{"stock_code":"2618","stock_name":"長榮航","ex_dividend_date":"07 / 08","ex_type":"息","cash_dividend_value":2.0,"current_yield_value":4.57,"closing_price_value":43.8,"pe_value":8.31,"pb_value":1.75},{"stock_code":"2634","stock_name":"漢翔","ex_dividend_date":"07 / 08","ex_type":"息","cash_dividend_value":0.778,"current_yield_value":1.58,"closing_price_value":49.2,"pe_value":61.5,"pb_value":2.55},{"stock_code":"3231","stock_name":"緯創","ex_dividend_date":"07 / 08","ex_type":"息","cash_dividend_value":5.500622,"current_yield_value":3.6,"closing_price_value":153.0,"pe_value":15.35,"pb_value":2.56},{"stock_code":"4148","stock_name":"全宇生技-KY","ex_dividend_date":"07 / 08","ex_type":"息","cash_dividend_value":1.0,"current_yield_value":3.39,"closing_price_value":29.5,"pe_value":13.66,"pb_value":0.73},{"stock_code":"4576","stock_name":"大銀微系統","ex_dividend_date":"07 / 08","ex_type":"息","cash_dividend_value":0.8,"current_yield_value":0.4,"closing_price_value":200.5,"pe_value":78.94,"pb_value":5.8},{"stock_code":"4904","stock_name":"遠傳","ex_dividend_date":"07 / 08","ex_type":"息","cash_dividend_value":3.809281,"current_yield_value":3.56,"closing_price_value":107.0,"pe_value":27.16,"pb_value":4.03},{"stock_code":"6641","stock_name":"基士德-KY","ex_dividend_date":"07 / 08","ex_type":"息","cash_dividend_value":0.4,"current_yield_value":2.23,"closing_price_value":17.95,"pe_value":37.4,"pb_value":0.43},{"stock_code":"6924","stock_name":"榮惠-KY創","ex_dividend_date":"07 / 08","ex_type":"息","cash_dividend_value":5.0,"current_yield_value":4.0,"closing_price_value":125.0,"pe_value":18.74,"pb_value":4.96},{"stock_code":"6937","stock_name":"天虹","ex_dividend_date":"07 / 08","ex_type":"息","cash_dividend_value":1.4,"current_yield_value":0.56,"closing_price_value":250.0,"pe_value":77.16,"pb_value":4.91},{"stock_code":"00400A","stock_name":"主動國泰動能高息","ex_dividend_date":"07 / 09","ex_type":"息","cash_dividend_value":null,"current_yield_value":null,"closing_price_value":null,"pe_value":null,"pb_value":null},{"stock_code":"00940","stock_name":"元大台灣價值高息","ex_dividend_date":"07 / 09","ex_type":"息","cash_dividend_value":null,"current_yield_value":null,"closing_price_value":null,"pe_value":null,"pb_value":null},{"stock_code":"1110","stock_name":"東泥","ex_dividend_date":"07 / 09","ex_type":"息","cash_dividend_value":0.3,"current_yield_value":2.01,"closing_price_value":14.9,"pe_value":46.56,"pb_value":0.9},{"stock_code":"1236","stock_name":"宏亞","ex_dividend_date":"07 / 09","ex_type":"息","cash_dividend_value":1.65,"current_yield_value":6.4,"closing_price_value":25.8,"pe_value":null,"pb_value":0.91},{"stock_code":"1256","stock_name":"鮮活果汁-KY","ex_dividend_date":"07 / 09","ex_type":"息","cash_dividend_value":6.6,"current_yield_value":3.73,"closing_price_value":177.0,"pe_value":13.37,"pb_value":1.52},{"stock_code":"1338","stock_name":"廣華-KY","ex_dividend_date":"07 / 09","ex_type":"息","cash_dividend_value":0.311445,"current_yield_value":1.88,"closing_price_value":16.6,"pe_value":null,"pb_value":0.23},{"stock_code":"1446","stock_name":"宏和","ex_dividend_date":"07 / 09","ex_type":"息","cash_dividend_value":1.5,"current_yield_value":9.12,"closing_price_value":16.45,"pe_value":9.68,"pb_value":0.8},{"stock_code":"1513","stock_name":"中興電","ex_dividend_date":"07 / 09","ex_type":"息","cash_dividend_value":6.0,"current_yield_value":3.42,"closing_price_value":175.5,"pe_value":21.32,"pb_value":4.03},{"stock_code":"1616","stock_name":"億泰","ex_dividend_date":"07 / 09","ex_type":"息","cash_dividend_value":1.3584,"current_yield_value":6.23,"closing_price_value":21.8,"pe_value":17.72,"pb_value":1.82},{"stock_code":"1723","stock_name":"中碳","ex_dividend_date":"07 / 09","ex_type":"息","cash_dividend_value":1.85,"current_yield_value":2.21,"closing_price_value":83.6,"pe_value":33.71,"pb_value":2.41},{"stock_code":"2412","stock_name":"中華電","ex_dividend_date":"07 / 09","ex_type":"息","cash_dividend_value":5.2,"current_yield_value":3.64,"closing_price_value":143.0,"pe_value":28.43,"pb_value":2.8},{"stock_code":"2453","stock_name":"凌群","ex_dividend_date":"07 / 09","ex_type":"息","cash_dividend_value":2.8,"current_yield_value":5.06,"closing_price_value":55.3,"pe_value":17.61,"pb_value":2.71},{"stock_code":"2478","stock_name":"大毅","ex_dividend_date":"07 / 09","ex_type":"息","cash_dividend_value":2.0,"current_yield_value":0.92,"closing_price_value":218.0,"pe_value":58.76,"pb_value":4.28},{"stock_code":"2488","stock_name":"漢平","ex_dividend_date":"07 / 09","ex_type":"息","cash_dividend_value":3.0,"current_yield_value":5.55,"closing_price_value":54.1,"pe_value":11.66,"pb_value":1.49},{"stock_code":"2492","stock_name":"華新科","ex_dividend_date":"07 / 09","ex_type":"息","cash_dividend_value":2.503091,"current_yield_value":0.46,"closing_price_value":540.0,"pe_value":103.45,"pb_value":4.9},{"stock_code":"2493","stock_name":"揚博","ex_dividend_date":"07 / 09","ex_type":"息","cash_dividend_value":4.0,"current_yield_value":1.47,"closing_price_value":272.0,"pe_value":64.3,"pb_value":11.88},{"stock_code":"2739","stock_name":"寒舍","ex_dividend_date":"07 / 09","ex_type":"息","cash_dividend_value":2.58,"current_yield_value":6.88,"closing_price_value":37.5,"pe_value":12.38,"pb_value":2.29},{"stock_code":"3014","stock_name":"聯陽","ex_dividend_date":"07 / 09","ex_type":"息","cash_dividend_value":8.50169,"current_yield_value":5.5,"closing_price_value":154.5,"pe_value":16.7,"pb_value":4.13},{"stock_code":"3024","stock_name":"憶聲","ex_dividend_date":"07 / 09","ex_type":"息","cash_dividend_value":0.22,"current_yield_value":1.83,"closing_price_value":12.0,"pe_value":133.33,"pb_value":1.1},{"stock_code":"3044","stock_name":"健鼎","ex_dividend_date":"07 / 09","ex_type":"息","cash_dividend_value":12.7,"current_yield_value":2.5,"closing_price_value":508.0,"pe_value":24.68,"pb_value":4.58},{"stock_code":"3045","stock_name":"台灣大","ex_dividend_date":"07 / 09","ex_type":"息","cash_dividend_value":4.74428,"current_yield_value":4.0,"closing_price_value":118.5,"pe_value":24.04,"pb_value":3.94},{"stock_code":"3060","stock_name":"銘異","ex_dividend_date":"07 / 09","ex_type":"息","cash_dividend_value":0.2,"current_yield_value":0.55,"closing_price_value":36.35,"pe_value":null,"pb_value":1.82},{"stock_code":"3167","stock_name":"大量","ex_dividend_date":"07 / 09","ex_type":"息","cash_dividend_value":3.914761,"current_yield_value":0.51,"closing_price_value":765.0,"pe_value":74.56,"pb_value":18.92},{"stock_code":"3588","stock_name":"通嘉","ex_dividend_date":"07 / 09","ex_type":"息","cash_dividend_value":0.498574,"current_yield_value":0.7,"closing_price_value":71.6,"pe_value":119.33,"pb_value":2.47},{"stock_code":"4590","stock_name":"富田-創","ex_dividend_date":"07 / 09","ex_type":"息","cash_dividend_value":2.3,"current_yield_value":3.14,"closing_price_value":73.2,"pe_value":28.82,"pb_value":1.14},{"stock_code":"4720","stock_name":"德淵","ex_dividend_date":"07 / 09","ex_type":"息","cash_dividend_value":0.4,"current_yield_value":1.79,"closing_price_value":22.4,"pe_value":36.72,"pb_value":1.58},{"stock_code":"5215","stock_name":"科嘉-KY","ex_dividend_date":"07 / 09","ex_type":"息","cash_dividend_value":2.0,"current_yield_value":4.66,"closing_price_value":42.95,"pe_value":17.53,"pb_value":0.77},{"stock_code":"5284","stock_name":"jpp-KY","ex_dividend_date":"07 / 09","ex_type":"權息","cash_dividend_value":5.0,"current_yield_value":1.41,"closing_price_value":355.0,"pe_value":26.49,"pb_value":4.91},{"stock_code":"5292","stock_name":"華懋","ex_dividend_date":"07 / 09","ex_type":"權息","cash_dividend_value":5.5,"current_yield_value":2.64,"closing_price_value":208.0,"pe_value":20.57,"pb_value":4.85},{"stock_code":"5469","stock_name":"瀚宇博","ex_dividend_date":"07 / 09","ex_type":"息","cash_dividend_value":2.521177,"current_yield_value":2.88,"closing_price_value":87.4,"pe_value":15.25,"pb_value":1.13},{"stock_code":"5533","stock_name":"皇鼎","ex_dividend_date":"07 / 09","ex_type":"息","cash_dividend_value":0.6,"current_yield_value":4.32,"closing_price_value":13.9,"pe_value":23.17,"pb_value":0.42},{"stock_code":"6115","stock_name":"鎰勝","ex_dividend_date":"07 / 09","ex_type":"息","cash_dividend_value":2.8,"current_yield_value":5.83,"closing_price_value":48.0,"pe_value":16.9,"pb_value":1.62},{"stock_code":"6166","stock_name":"凌華","ex_dividend_date":"07 / 09","ex_type":"息","cash_dividend_value":1.198986,"current_yield_value":0.84,"closing_price_value":142.0,"pe_value":39.34,"pb_value":5.35},{"stock_code":"6191","stock_name":"精成科","ex_dividend_date":"07 / 09","ex_type":"息","cash_dividend_value":2.6,"current_yield_value":2.59,"closing_price_value":100.5,"pe_value":15.65,"pb_value":1.81},{"stock_code":"6278","stock_name":"台表科","ex_dividend_date":"07 / 09","ex_type":"息","cash_dividend_value":5.564956,"current_yield_value":2.92,"closing_price_value":190.5,"pe_value":21.75,"pb_value":2.48},{"stock_code":"6446","stock_name":"藥華藥","ex_dividend_date":"07 / 09","ex_type":"權息","cash_dividend_value":1.490152,"current_yield_value":0.13,"closing_price_value":1155.0,"pe_value":72.41,"pb_value":12.47},{"stock_code":"6605","stock_name":"帝寶","ex_dividend_date":"07 / 09","ex_type":"息","cash_dividend_value":6.5,"current_yield_value":4.74,"closing_price_value":137.0,"pe_value":10.27,"pb_value":1.1},{"stock_code":"6781","stock_name":"AES-KY","ex_dividend_date":"07 / 09","ex_type":"息","cash_dividend_value":19.1,"current_yield_value":1.73,"closing_price_value":1105.0,"pe_value":28.24,"pb_value":5.22},{"stock_code":"8110","stock_name":"華東","ex_dividend_date":"07 / 09","ex_type":"息","cash_dividend_value":1.494171,"current_yield_value":2.62,"closing_price_value":57.0,"pe_value":20.88,"pb_value":2.33},{"stock_code":"8261","stock_name":"富鼎","ex_dividend_date":"07 / 09","ex_type":"息","cash_dividend_value":5.0,"current_yield_value":2.05,"closing_price_value":244.0,"pe_value":41.78,"pb_value":4.74},{"stock_code":"8374","stock_name":"羅昇","ex_dividend_date":"07 / 09","ex_type":"息","cash_dividend_value":0.2,"current_yield_value":0.24,"closing_price_value":84.0,"pe_value":null,"pb_value":4.66},{"stock_code":"8499","stock_name":"鼎炫-KY","ex_dividend_date":"07 / 09","ex_type":"息","cash_dividend_value":8.0,"current_yield_value":2.67,"closing_price_value":300.0,"pe_value":30.06,"pb_value":1.44},{"stock_code":"9905","stock_name":"大華","ex_dividend_date":"07 / 09","ex_type":"息","cash_dividend_value":1.1,"current_yield_value":5.21,"closing_price_value":21.1,"pe_value":14.96,"pb_value":0.76},{"stock_code":"2008","stock_name":"高興昌","ex_dividend_date":"07 / 10","ex_type":"息","cash_dividend_value":1.0,"current_yield_value":3.33,"closing_price_value":30.05,"pe_value":40.07,"pb_value":1.52},{"stock_code":"2610","stock_name":"華航","ex_dividend_date":"07 / 10","ex_type":"息","cash_dividend_value":0.814457,"current_yield_value":3.51,"closing_price_value":23.2,"pe_value":9.06,"pb_value":1.38},{"stock_code":"2891","stock_name":"中信金","ex_dividend_date":"07 / 10","ex_type":"息","cash_dividend_value":2.500239,"current_yield_value":3.56,"closing_price_value":70.3,"pe_value":16.94,"pb_value":2.51},{"stock_code":"2891B","stock_name":"中信金乙特","ex_dividend_date":"07 / 10","ex_type":"息","cash_dividend_value":2.796,"current_yield_value":null,"closing_price_value":null,"pe_value":null,"pb_value":null},{"stock_code":"2891C","stock_name":"中信金丙特","ex_dividend_date":"07 / 10","ex_type":"息","cash_dividend_value":1.92,"current_yield_value":null,"closing_price_value":null,"pe_value":null,"pb_value":null},{"stock_code":"3034","stock_name":"聯詠","ex_dividend_date":"07 / 10","ex_type":"息","cash_dividend_value":23.0,"current_yield_value":4.52,"closing_price_value":509.0,"pe_value":20.86,"pb_value":4.31},{"stock_code":"3055","stock_name":"蔚華科","ex_dividend_date":"07 / 10","ex_type":"息","cash_dividend_value":0.5,"current_yield_value":0.52,"closing_price_value":96.0,"pe_value":null,"pb_value":6.67},{"stock_code":"4968","stock_name":"立積","ex_dividend_date":"07 / 10","ex_type":"息","cash_dividend_value":1.6,"current_yield_value":1.45,"closing_price_value":110.5,"pe_value":37.33,"pb_value":3.63},{"stock_code":"5519","stock_name":"隆大","ex_dividend_date":"07 / 10","ex_type":"權息","cash_dividend_value":3.3,"current_yield_value":9.71,"closing_price_value":34.0,"pe_value":6.81,"pb_value":1.33},{"stock_code":"6477","stock_name":"安集","ex_dividend_date":"07 / 10","ex_type":"息","cash_dividend_value":0.35,"current_yield_value":1.18,"closing_price_value":29.6,"pe_value":328.89,"pb_value":1.17},{"stock_code":"1907","stock_name":"永豐餘","ex_dividend_date":"07 / 13","ex_type":"息","cash_dividend_value":1.0,"current_yield_value":3.7,"closing_price_value":27.0,"pe_value":19.29,"pb_value":0.57},{"stock_code":"2248","stock_name":"華勝-KY","ex_dividend_date":"07 / 13","ex_type":"息","cash_dividend_value":3.1055,"current_yield_value":5.68,"closing_price_value":54.7,"pe_value":9.24,"pb_value":1.45},{"stock_code":"2316","stock_name":"楠梓電","ex_dividend_date":"07 / 13","ex_type":"息","cash_dividend_value":2.0,"current_yield_value":0.87,"closing_price_value":230.0,"pe_value":14.9,"pb_value":3.04},{"stock_code":"2347","stock_name":"聯強","ex_dividend_date":"07 / 13","ex_type":"息","cash_dividend_value":4.2,"current_yield_value":4.53,"closing_price_value":92.8,"pe_value":16.14,"pb_value":1.97},{"stock_code":"2359","stock_name":"所羅門","ex_dividend_date":"07 / 13","ex_type":"息","cash_dividend_value":1.0,"current_yield_value":0.79,"closing_price_value":126.5,"pe_value":65.21,"pb_value":3.77},{"stock_code":"2645","stock_name":"長榮航太","ex_dividend_date":"07 / 13","ex_type":"息","cash_dividend_value":5.0,"current_yield_value":2.93,"closing_price_value":170.5,"pe_value":26.03,"pb_value":5.04},{"stock_code":"4306","stock_name":"炎洲","ex_dividend_date":"07 / 13","ex_type":"息","cash_dividend_value":0.7,"current_yield_value":4.4,"closing_price_value":15.9,"pe_value":41.84,"pb_value":0.83},{"stock_code":"4999","stock_name":"鑫禾","ex_dividend_date":"07 / 13","ex_type":"息","cash_dividend_value":0.25,"current_yield_value":1.25,"closing_price_value":20.0,"pe_value":null,"pb_value":0.46},{"stock_code":"6790","stock_name":"永豐實","ex_dividend_date":"07 / 13","ex_type":"息","cash_dividend_value":2.65,"current_yield_value":6.61,"closing_price_value":40.1,"pe_value":13.06,"pb_value":1.76},{"stock_code":"6890","stock_name":"來億-KY","ex_dividend_date":"07 / 13","ex_type":"息","cash_dividend_value":8.967789,"current_yield_value":4.01,"closing_price_value":223.5,"pe_value":22.11,"pb_value":2.25},{"stock_code":"6951","stock_name":"青新-創","ex_dividend_date":"07 / 13","ex_type":"權","cash_dividend_value":0.0,"current_yield_value":null,"closing_price_value":77.0,"pe_value":13.39,"pb_value":3.43},{"stock_code":"7610","stock_name":"聯友金屬-創","ex_dividend_date":"07 / 13","ex_type":"權息","cash_dividend_value":0.5,"current_yield_value":0.02,"closing_price_value":2025.0,"pe_value":125.39,"pb_value":46.35},{"stock_code":"8103","stock_name":"瀚荃","ex_dividend_date":"07 / 13","ex_type":"息","cash_dividend_value":2.8,"current_yield_value":2.94,"closing_price_value":95.2,"pe_value":20.52,"pb_value":1.93},{"stock_code":"1402","stock_name":"遠東新","ex_dividend_date":"07 / 14","ex_type":"息","cash_dividend_value":1.25,"current_yield_value":4.39,"closing_price_value":28.5,"pe_value":17.7,"pb_value":0.65},{"stock_code":"1603","stock_name":"華電","ex_dividend_date":"07 / 14","ex_type":"息","cash_dividend_value":2.0,"current_yield_value":6.43,"closing_price_value":31.1,"pe_value":11.56,"pb_value":0.65},{"stock_code":"2027","stock_name":"大成鋼","ex_dividend_date":"07 / 14","ex_type":"息","cash_dividend_value":1.5,"current_yield_value":3.76,"closing_price_value":39.9,"pe_value":11.67,"pb_value":1.19},{"stock_code":"2029","stock_name":"盛餘","ex_dividend_date":"07 / 14","ex_type":"息","cash_dividend_value":0.6,"current_yield_value":2.92,"closing_price_value":20.55,"pe_value":33.15,"pb_value":0.66},{"stock_code":"2501","stock_name":"國建","ex_dividend_date":"07 / 14","ex_type":"息","cash_dividend_value":1.2,"current_yield_value":4.97,"closing_price_value":24.15,"pe_value":6.24,"pb_value":0.89},{"stock_code":"2609","stock_name":"陽明","ex_dividend_date":"07 / 14","ex_type":"息","cash_dividend_value":2.0,"current_yield_value":3.99,"closing_price_value":50.1,"pe_value":16.27,"pb_value":0.53},{"stock_code":"2633","stock_name":"台灣高鐵","ex_dividend_date":"07 / 14","ex_type":"息","cash_dividend_value":1.15,"current_yield_value":4.41,"closing_price_value":26.05,"pe_value":21.53,"pb_value":1.96},{"stock_code":"2836A","stock_name":"高雄銀甲特","ex_dividend_date":"07 / 14","ex_type":"息","cash_dividend_value":0.775,"current_yield_value":null,"closing_price_value":null,"pe_value":null,"pb_value":null},{"stock_code":"3013","stock_name":"晟銘電","ex_dividend_date":"07 / 14","ex_type":"息","cash_dividend_value":0.4,"current_yield_value":0.39,"closing_price_value":103.0,"pe_value":22.59,"pb_value":3.84},{"stock_code":"3130","stock_name":"一零四","ex_dividend_date":"07 / 14","ex_type":"息","cash_dividend_value":14.70435,"current_yield_value":6.67,"closing_price_value":220.5,"pe_value":14.62,"pb_value":4.01},{"stock_code":"3150","stock_name":"鈺寶-創","ex_dividend_date":"07 / 14","ex_type":"息","cash_dividend_value":0.5,"current_yield_value":2.66,"closing_price_value":18.8,"pe_value":null,"pb_value":1.43},{"stock_code":"3645","stock_name":"達邁","ex_dividend_date":"07 / 14","ex_type":"息","cash_dividend_value":1.2,"current_yield_value":1.38,"closing_price_value":87.1,"pe_value":45.84,"pb_value":3.51},{"stock_code":"3717","stock_name":"聯嘉投控","ex_dividend_date":"07 / 14","ex_type":"息","cash_dividend_value":0.197058,"current_yield_value":0.83,"closing_price_value":23.6,"pe_value":295.0,"pb_value":1.46},{"stock_code":"4588","stock_name":"玖鼎電力","ex_dividend_date":"07 / 14","ex_type":"息","cash_dividend_value":3.0,"current_yield_value":5.23,"closing_price_value":57.4,"pe_value":16.12,"pb_value":2.58},{"stock_code":"5471","stock_name":"松翰","ex_dividend_date":"07 / 14","ex_type":"息","cash_dividend_value":0.8,"current_yield_value":1.37,"closing_price_value":58.5,"pe_value":60.31,"pb_value":2.76},{"stock_code":"6698","stock_name":"旭暉應材","ex_dividend_date":"07 / 14","ex_type":"息","cash_dividend_value":0.5,"current_yield_value":1.18,"closing_price_value":42.2,"pe_value":null,"pb_value":2.59},{"stock_code":"1563","stock_name":"巧新","ex_dividend_date":"07 / 15","ex_type":"息","cash_dividend_value":2.0,"current_yield_value":3.11,"closing_price_value":64.4,"pe_value":146.36,"pb_value":1.7},{"stock_code":"2228","stock_name":"劍麟","ex_dividend_date":"07 / 15","ex_type":"息","cash_dividend_value":4.5,"current_yield_value":5.35,"closing_price_value":84.1,"pe_value":19.7,"pb_value":1.29},{"stock_code":"2636","stock_name":"台驊控股","ex_dividend_date":"07 / 15","ex_type":"息","cash_dividend_value":5.0,"current_yield_value":7.33,"closing_price_value":68.2,"pe_value":9.99,"pb_value":0.99},{"stock_code":"3652","stock_name":"精聯","ex_dividend_date":"07 / 15","ex_type":"息","cash_dividend_value":1.195417,"current_yield_value":3.02,"closing_price_value":39.55,"pe_value":28.25,"pb_value":1.58},{"stock_code":"6614","stock_name":"資拓宏宇","ex_dividend_date":"07 / 15","ex_type":"息","cash_dividend_value":1.65,"current_yield_value":4.16,"closing_price_value":39.65,"pe_value":15.92,"pb_value":2.14},{"stock_code":"9908","stock_name":"大台北","ex_dividend_date":"07 / 15","ex_type":"息","cash_dividend_value":1.2,"current_yield_value":4.06,"closing_price_value":29.55,"pe_value":16.69,"pb_value":1.0},{"stock_code":"1102","stock_name":"亞泥","ex_dividend_date":"07 / 16","ex_type":"息","cash_dividend_value":2.3,"current_yield_value":6.43,"closing_price_value":35.75,"pe_value":12.0,"pb_value":0.72},{"stock_code":"1109","stock_name":"信大","ex_dividend_date":"07 / 16","ex_type":"息","cash_dividend_value":0.9,"current_yield_value":6.16,"closing_price_value":14.6,"pe_value":18.48,"pb_value":0.59},{"stock_code":"1440","stock_name":"南紡","ex_dividend_date":"07 / 16","ex_type":"息","cash_dividend_value":0.3,"current_yield_value":2.31,"closing_price_value":13.0,"pe_value":null,"pb_value":0.78},{"stock_code":"1522","stock_name":"堤維西","ex_dividend_date":"07 / 16","ex_type":"息","cash_dividend_value":1.2,"current_yield_value":4.02,"closing_price_value":29.85,"pe_value":96.29,"pb_value":1.01},{"stock_code":"1522A","stock_name":"堤維西甲特","ex_dividend_date":"07 / 16","ex_type":"息","cash_dividend_value":2.0,"current_yield_value":null,"closing_price_value":null,"pe_value":null,"pb_value":null},{"stock_code":"1614","stock_name":"三洋電","ex_dividend_date":"07 / 16","ex_type":"息","cash_dividend_value":0.967772,"current_yield_value":3.08,"closing_price_value":31.4,"pe_value":23.79,"pb_value":1.46},{"stock_code":"2404","stock_name":"漢唐","ex_dividend_date":"07 / 16","ex_type":"息","cash_dividend_value":40.0,"current_yield_value":2.99,"closing_price_value":1340.0,"pe_value":24.91,"pb_value":17.59},{"stock_code":"2506","stock_name":"太設","ex_dividend_date":"07 / 16","ex_type":"息","cash_dividend_value":0.2,"current_yield_value":2.28,"closing_price_value":8.78,"pe_value":null,"pb_value":0.4},{"stock_code":"4560","stock_name":"強信-KY","ex_dividend_date":"07 / 20","ex_type":"息","cash_dividend_value":2.0,"current_yield_value":6.17,"closing_price_value":32.4,"pe_value":11.33,"pb_value":1.05},{"stock_code":"8213","stock_name":"志超","ex_dividend_date":"07 / 20","ex_type":"息","cash_dividend_value":1.14,"current_yield_value":3.2,"closing_price_value":35.65,"pe_value":18.47,"pb_value":0.58},{"stock_code":"8481","stock_name":"政伸","ex_dividend_date":"07 / 20","ex_type":"息","cash_dividend_value":2.75,"current_yield_value":6.65,"closing_price_value":41.35,"pe_value":13.56,"pb_value":1.68},{"stock_code":"1233","stock_name":"天仁","ex_dividend_date":"07 / 21","ex_type":"息","cash_dividend_value":0.2,"current_yield_value":0.71,"closing_price_value":28.2,"pe_value":34.39,"pb_value":1.83},{"stock_code":"1535","stock_name":"中宇","ex_dividend_date":"07 / 21","ex_type":"息","cash_dividend_value":3.0,"current_yield_value":6.03,"closing_price_value":49.75,"pe_value":12.79,"pb_value":1.55},{"stock_code":"1726","stock_name":"永記","ex_dividend_date":"07 / 21","ex_type":"息","cash_dividend_value":3.7,"current_yield_value":4.72,"closing_price_value":78.4,"pe_value":13.22,"pb_value":1.17},{"stock_code":"2704","stock_name":"國賓","ex_dividend_date":"07 / 21","ex_type":"息","cash_dividend_value":0.5,"current_yield_value":1.14,"closing_price_value":44.0,"pe_value":24.58,"pb_value":0.61},{"stock_code":"2906","stock_name":"高林","ex_dividend_date":"07 / 22","ex_type":"息","cash_dividend_value":0.6,"current_yield_value":4.23,"closing_price_value":14.2,"pe_value":31.56,"pb_value":0.88},{"stock_code":"1201","stock_name":"味全","ex_dividend_date":"07 / 23","ex_type":"息","cash_dividend_value":0.21,"current_yield_value":1.72,"closing_price_value":12.2,"pe_value":32.11,"pb_value":0.79},{"stock_code":"1227","stock_name":"佳格","ex_dividend_date":"07 / 23","ex_type":"息","cash_dividend_value":1.34,"current_yield_value":4.61,"closing_price_value":29.05,"pe_value":19.9,"pb_value":1.38},{"stock_code":"1417","stock_name":"嘉裕","ex_dividend_date":"07 / 23","ex_type":"息","cash_dividend_value":0.25,"current_yield_value":2.99,"closing_price_value":8.35,"pe_value":18.56,"pb_value":0.68},{"stock_code":"1503","stock_name":"士電","ex_dividend_date":"07 / 23","ex_type":"息","cash_dividend_value":5.0,"current_yield_value":2.14,"closing_price_value":233.5,"pe_value":34.8,"pb_value":3.2},{"stock_code":"1558","stock_name":"伸興","ex_dividend_date":"07 / 23","ex_type":"息","cash_dividend_value":5.0,"current_yield_value":5.56,"closing_price_value":90.0,"pe_value":16.01,"pb_value":1.09},{"stock_code":"1590","stock_name":"亞德客-KY","ex_dividend_date":"07 / 23","ex_type":"息","cash_dividend_value":29.1078,"current_yield_value":2.14,"closing_price_value":1360.0,"pe_value":29.77,"pb_value":5.35},{"stock_code":"2414","stock_name":"精技","ex_dividend_date":"07 / 23","ex_type":"息","cash_dividend_value":3.0,"current_yield_value":5.11,"closing_price_value":58.7,"pe_value":16.63,"pb_value":2.78},{"stock_code":"2002","stock_name":"中鋼","ex_dividend_date":"07 / 24","ex_type":"息","cash_dividend_value":0.15,"current_yield_value":0.79,"closing_price_value":19.0,"pe_value":null,"pb_value":0.98},{"stock_code":"2002A","stock_name":"中鋼特","ex_dividend_date":"07 / 24","ex_type":"息","cash_dividend_value":1.4,"current_yield_value":null,"closing_price_value":null,"pe_value":null,"pb_value":null},{"stock_code":"6796","stock_name":"晉弘","ex_dividend_date":"07 / 24","ex_type":"息","cash_dividend_value":0.25,"current_yield_value":0.44,"closing_price_value":56.5,"pe_value":null,"pb_value":2.61},{"stock_code":"5871","stock_name":"中租-KY","ex_dividend_date":"07 / 29","ex_type":"權息","cash_dividend_value":5.8,"current_yield_value":5.11,"closing_price_value":113.5,"pe_value":10.63,"pb_value":1.11},{"stock_code":"5871A","stock_name":"中租-KY甲特","ex_dividend_date":"07 / 29","ex_type":"息","cash_dividend_value":4.179463,"current_yield_value":null,"closing_price_value":null,"pe_value":null,"pb_value":null},{"stock_code":"9942","stock_name":"茂順","ex_dividend_date":"07 / 30","ex_type":"息","cash_dividend_value":7.0,"current_yield_value":6.01,"closing_price_value":116.5,"pe_value":14.19,"pb_value":2.14},{"stock_code":"2376","stock_name":"技嘉","ex_dividend_date":"08 / 03","ex_type":"息","cash_dividend_value":12.0,"current_yield_value":3.76,"closing_price_value":319.5,"pe_value":14.92,"pb_value":3.32},{"stock_code":"1342","stock_name":"八貫","ex_dividend_date":"08 / 04","ex_type":"權","cash_dividend_value":0.0,"current_yield_value":null,"closing_price_value":111.0,"pe_value":18.66,"pb_value":4.14},{"stock_code":"3533","stock_name":"嘉澤","ex_dividend_date":"08 / 04","ex_type":"息","cash_dividend_value":34.93436,"current_yield_value":1.66,"closing_price_value":2105.0,"pe_value":29.58,"pb_value":5.63},{"stock_code":"9938","stock_name":"百和","ex_dividend_date":"08 / 04","ex_type":"息","cash_dividend_value":3.0,"current_yield_value":6.94,"closing_price_value":43.25,"pe_value":12.57,"pb_value":1.0},{"stock_code":"6201","stock_name":"亞弘電","ex_dividend_date":"08 / 05","ex_type":"息","cash_dividend_value":3.1,"current_yield_value":6.45,"closing_price_value":48.05,"pe_value":14.6,"pb_value":1.64},{"stock_code":"6491","stock_name":"晶碩","ex_dividend_date":"08 / 07","ex_type":"息","cash_dividend_value":10.0,"current_yield_value":3.11,"closing_price_value":322.0,"pe_value":15.48,"pb_value":2.23},{"stock_code":"2520","stock_name":"冠德","ex_dividend_date":"08 / 10","ex_type":"息","cash_dividend_value":1.615933,"current_yield_value":4.74,"closing_price_value":34.1,"pe_value":14.15,"pb_value":0.84},{"stock_code":"1618","stock_name":"合機","ex_dividend_date":"08 / 17","ex_type":"息","cash_dividend_value":1.7,"current_yield_value":4.29,"closing_price_value":39.6,"pe_value":8.7,"pb_value":1.19}]}